docuhook/__init__.py
docuhook/ai_client.py
docuhook/code_analyzer.py
docuhook/main.py
docuhook-0.1.1.dist-info/LICENSE
docuhook-0.1.1.dist-info/METADATA
docuhook-0.1.1.dist-info/WHEEL
docuhook-0.1.1.dist-info/entry_points.txt
docuhook-0.1.1.dist-info/RECORD
