Metadata-Version: 2.3
Name: docuhook
Version: 0.1.1
Summary: A pre-commit hook that uses AI to automatically generate Python docstrings.
License: MIT License
Author: Bartosz Borowski
Author-email: contact@bborowski.pl
Requires-Python: >=3.13
Classifier: License :: Other/Proprietary License
Classifier: Programming Language :: Python :: 3
Classifier: Programming Language :: Python :: 3.13
Requires-Dist: pre-commit (>=4.2.0,<5.0.0)
Requires-Dist: pytest (>=8.4.1,<9.0.0)
Requires-Dist: requests (>=2.32.4,<3.0.0)
Project-URL: Homepage, https://github.com/bartoszborowski/docuhook
Project-URL: Repository, https://github.com/bartoszborowski/docuhook
